the_spymaster_solvers_client/__init__.py
the_spymaster_solvers_client/client.py
the_spymaster_solvers_client/structs/__init__.py
the_spymaster_solvers_client/structs/base.py
the_spymaster_solvers_client/structs/errors.py
the_spymaster_solvers_client/structs/requests.py
the_spymaster_solvers_client/structs/responses.py
the_spymaster_solvers_client-2.0.0.dist-info/METADATA
the_spymaster_solvers_client-2.0.0.dist-info/WHEEL
the_spymaster_solvers_client-2.0.0.dist-info/top_level.txt
the_spymaster_solvers_client-2.0.0.dist-info/RECORD
