Metadata-Version: 2.1
Name: the-spymaster-solvers-client
Version: 2.0.0
Summary: Python client implementation for The Spymaster Solvers HTTP backend.
Home-page: https://github.com/asaf-kali/the-spymaster-solvers
Author: Asaf Kali
Author-email: asaf.kali@mail.huji.ac.il
Requires-Python: >=3.6
Requires-Dist: codenames ~=4.0
Requires-Dist: the-spymaster-util ~=3.0
Requires-Dist: pydantic ~=1.9
Requires-Dist: requests ~=2.28
